README.rst
setup.cfg
setup.py
nhlrank/__init__.py
nhlrank/__main__.py
nhlrank/constants.py
nhlrank/core.py
nhlrank/env.py
nhlrank/sheetutils.py
nhlrank/standings.py
nhlrank/utils.py
nhlrank.egg-info/PKG-INFO
nhlrank.egg-info/SOURCES.txt
nhlrank.egg-info/dependency_links.txt
nhlrank.egg-info/entry_points.txt
nhlrank.egg-info/not-zip-safe
nhlrank.egg-info/requires.txt
nhlrank.egg-info/top_level.txt
nhlrank/argparser/__init__.py
nhlrank/argparser/funcs.py
nhlrank/argparser/types.py
nhlrank/glicko2/__init__.py
nhlrank/glicko2/glicko2.py
nhlrank/glicko2/setup.py
nhlrank/models/__init__.py
nhlrank/models/helpers.py
scripts/hk