Metadata-Version: 2.1
Name: nhlrank
Version: 0.0.1.dev15
Summary: Analytics software for NHL teams data past and present
Home-page: https://github.com/nutratech/nhlrank
Author: Shane J
Author-email: chown_tee@proton.me
License: Apache License (2.0)
Platform: linux
Platform: darwin
Platform: win32
Classifier: Environment :: Console
Classifier: Intended Audience :: End Users/Desktop
Classifier: Intended Audience :: Science/Research
Classifier: Intended Audience :: Education
Classifier: Development Status :: 3 - Alpha
Classifier: Natural Language :: English
Classifier: License :: OSI Approved :: Apache Software License
Classifier: Framework :: Flake8
Classifier: Framework :: Pytest
Classifier: Operating System :: OS Independent
Classifier: Operating System :: Microsoft :: Windows :: Windows XP
Classifier: Operating System :: Microsoft :: Windows :: Windows 10
Classifier: Operating System :: MacOS :: MacOS X
Classifier: Operating System :: POSIX :: Linux
Classifier: Programming Language :: Python :: Implementation :: CPython
Classifier: Programming Language :: Python :: Implementation :: PyPy
Classifier: Programming Language :: Python :: 3 :: Only
Classifier: Programming Language :: Python :: 3.4
Classifier: Programming Language :: Python :: 3.11
Classifier: Programming Language :: SQL
Classifier: Programming Language :: Unix Shell
Requires-Python: >=3.10.0
Provides-Extra: extras
